<?xml version="1.0" encoding="UTF-8"?>
<?xml-stylesheet type="text/xsl" href="../../xslt/statblock.xsl"?>

<encounter>
  <info>
    <name>Calmor Vael</name>
    <file>MK02-15-00.xml</file>
    <abenteuer>MK02-15 Calmor Vael Endboss</abenteuer>
    <kampagne>MK02 - Die Jagd nach Calmor Vael</kampagne>
  </info>

<statblock name="Calmor Vael – Wiedererweckter Zauberer Zhaitans" id="ID_D4T_NPC_CALMOR_VAEL">
  <meta>
    <size>Mittel</size>
    <type>Untoter</type>
    <alignment>neutral böse</alignment>
    <ac>16 (magisch verstärkte Robe)</ac>
    <hp>130 (20W8 + 40)</hp>
    <speed>9 m</speed>
    <senses>Dunkelsicht 18 m, passive Wahrnehmung 13</senses>
    <languages>Tyrianisch, Alt-Tyrianisch; Telepathie 18 m</languages>
    <challenge>7 (2.900 EP)</challenge>
    <resistances>Nekrotisch, Kälte, Feuer, Gift</resistances>
    <immunities>Krankheit</immunities>
    <conditionImmunities>Erschöpfung, Bezaubert, Verängstigt</conditionImmunities>
  </meta>

  <abilities>
    <ability name="Str" score="10" bonus="+0"/>
    <ability name="Dex" score="14" bonus="+2"/>
    <ability name="Con" score="16" bonus="+3"/>
    <ability name="Int" score="18" bonus="+4"/>
    <ability name="Wis" score="16" bonus="+3"/>
    <ability name="Cha" score="20" bonus="+5"/>
  </abilities>

  <saves>
    <save ability="Int" bonus="+8"/>
    <save ability="Wis" bonus="+7"/>
    <save ability="Cha" bonus="+9"/>
  </saves>

  <skills>
    <!-- Optional: weitere Skills nach Bedarf -->
    <skill name="Arkane Kunde" bonus="+8"/>
    <skill name="Täuschen" bonus="+9"/>
    <skill name="Wahrnehmung" bonus="+7"/>
  </skills>

  <traits>
    <trait name="Untote Natur">
      <description>Calmor braucht weder Luft, Nahrung noch Schlaf.</description>
    </trait>
    <trait name="Legendäre Resistenz (3/Tag)">
      <description>Wenn Calmor bei einem Rettungswurf scheitert, kann er stattdessen erfolgreich bestehen.</description>
    </trait>
    <trait name="Schattenversteck (1/Tag)">
      <description>Calmor umhüllt sich mit Spurlosigkeit (Pass without Trace) für bis zu 1 Stunde, ohne Konzentration aufzugeben, selbst wenn er konzentrierte Zauber wirkt.</description>
    </trait>
    <trait name="Legendäre Aktionen">
      <description>Calmor kann pro Runde 2 legendäre Aktionen einsetzen, jeweils am Ende eines Zuges eines anderen Wesens. Er kann pro Runde nur eine legendäre Aktion-Option verwenden und erhält verbrauchte Aktionen zu Beginn seines Zuges zurück:
      • Zaubertrick: Wirkt einen Zaubertrick (z. B. Feuerpfeil/Grabesberührung). 
      • Schattenversatz: Teleportiert sich bis zu 9 m zu einem freien Platz, den er sehen kann.
      • Erschreckender Blick (Kosten: 2 Aktionen): Eine Kreatur in 9 m muss einen WIS-Rettungswurf bestehen oder ist bis zum Ende von Calmors nächstem Zug verängstigt.</description>
    </trait>
  </traits>

  <actions>
    <action name="Grimm der Nebel (Mehrfachangriff mit Zaubertricks)">
      <description>Calmor wirkt zweimal pro Runde einen Zaubertrick (meist Feuerpfeil gegen entfernte Ziele oder Grabesberührung gegen Heiler/Untote-Interaktionen).</description>
    </action>
  </actions>

  <reactions>
    <reaction name="Instinktiver Schild">
      <description>Wenn Calmor von einem Angriff getroffen würde, wirkt er <i>Schild (Shield)</i> und erhöht seine RK bis zum Beginn seines nächsten Zuges um +5.</description>
    </reaction>
    <reaction name="Gegenzauber">
      <description>Calmor wirkt <i>Gegenzauber (Counterspell)</i>, um einen Zauber zu unterbrechen, sofern er einen passenden Slot übrig hat.</description>
    </reaction>
  </reactions>

  <spellcasting>
    <stat>Cha</stat>
    <saveDC>17</saveDC>
    <attackBonus>+9</attackBonus>
    <spelllist>
      <spell level="0" id="ID_D4T_SPELL_THAUMATURGY">Thaumaturgie (Thaumaturgy)</spell>
      <spell level="0" id="ID_D4T_SPELL_MINOR_ILLUSION">Einfache Illusion (Minor Illusion)</spell>
      <spell level="0" id="ID_D4T_SPELL_FIRE_BOLT">Feuerpfeil (Fire Bolt)</spell>
      <spell level="0" id="ID_D4T_SPELL_CHILL_TOUCH">Kalte Hand (Chill Touch)</spell>

      <spell level="1" id="ID_D4T_SPELL_SHIELD">Schild (Shield)</spell>
      <spell level="1" id="ID_D4T_SPELL_MAGIC_MISSILE">Magisches Geschoss (Magic Missile)</spell>
      <spell level="1" id="ID_D4T_SPELL_WITCH_BOLT">Hexenpfeil (Witch Bolt)</spell>

      <spell level="2" id="ID_D4T_SPELL_MISTY_STEP">Nebelschritt (Misty Step)</spell>
      <spell level="2" id="ID_D4T_SPELL_MIRROR_IMAGE">Spiegelbilder (Mirror Image)</spell>
      <spell level="2" id="ID_D4T_SPELL_SCORCHING_RAY">Sengender Strahl (Scorching Ray)</spell>

      <spell level="3" id="ID_D4T_SPELL_COUNTERSPELL">Gegenzauber (Counterspell)</spell>
      <spell level="3" id="ID_D4T_SPELL_DISPEL_MAGIC">Magie bannen (Dispel Magic)</spell>
      <spell level="3" id="ID_D4T_SPELL_FIREBALL">Feuerball (Fireball)</spell>

      <spell level="4" id="ID_D4T_SPELL_GREATER_INVISIBILITY">Mächtige Unsichtbarkeit (Greater Invisibility)</spell>
      <spell level="4" id="ID_D4T_SPELL_DIMENSION_DOOR">Dimensionstür (Dimension Door)</spell>
      <spell level="4" id="ID_D4T_SPELL_BLIGHT">Dürre (Blight)</spell>

      <spell level="5" id="ID_D4T_SPELL_WALL_OF_FORCE">Energiewand (Wall of Force)</spell>
      <spell level="5" id="ID_D4T_SPELL_CLOUDKILL">Todeswolke (Cloudkill)</spell>
      <!--<spell level="5" id="">Synaptische Störung (Synaptic Static)</spell>-->
      <spell level="5" id="ID_D4T_SPELL_HOLD_MONSTER">Monster festhalten (Hold Monster)</spell>
      <spell level="5" id="ID_D4T_SPELL_GEAS">Geas</spell>

      <spell level="6" id="ID_D4T_SPELL_GLOBE_OF_INVULNERABILITY">Kugel der Unverwundbarkeit (Globe of Invulnerability)</spell>

      <spell level="7" id="ID_D4T_SPELL_PLANE_SHIFT">Finger des Todes (Finger of Death)</spell>

      <spell level="8" id="ID_D4T_SPELL_TELEPORT">Teleportieren (Teleport)</spell>
    </spelllist>
    <slots>
      <slot level="1" count="4"/>
      <slot level="2" count="3"/>
      <slot level="3" count="3"/>
      <slot level="4" count="3"/>
      <slot level="5" count="2"/>
      <slot level="6" count="1"/>
      <slot level="7" count="1"/>
      <slot level="8" count="1"/>
    </slots>
  </spellcasting>
</statblock>

</encounter>
